valkey_glide-2.2.6.dist-info/METADATA
valkey_glide-2.2.6.dist-info/WHEEL
glide/async_commands/glide_json.py
glide/async_commands/ft.py
glide/async_commands/__init__.py
glide/async_commands/core.py
glide/async_commands/standalone_commands.py
glide/async_commands/cluster_commands.py
glide/__init__.py
glide/glide.pyi
glide/opentelemetry.py
glide/glide_client.py
glide/logger.py
glide/py.typed
glide_shared/__init__.py
glide_shared/commands/__init__.py
glide_shared/commands/batch.py
glide_shared/commands/batch_options.py
glide_shared/commands/bitmap.py
glide_shared/commands/command_args.py
glide_shared/commands/core_options.py
glide_shared/commands/server_modules/ft_options/ft_aggregate_options.py
glide_shared/commands/server_modules/ft_options/ft_constants.py
glide_shared/commands/server_modules/ft_options/ft_create_options.py
glide_shared/commands/server_modules/ft_options/ft_profile_options.py
glide_shared/commands/server_modules/ft_options/ft_search_options.py
glide_shared/commands/server_modules/json_batch.py
glide_shared/commands/server_modules/json_options.py
glide_shared/commands/sorted_set.py
glide_shared/commands/stream.py
glide_shared/config.py
glide_shared/constants.py
glide_shared/exceptions.py
glide_shared/protobuf/command_request_pb2.py
glide_shared/protobuf/connection_request_pb2.py
glide_shared/protobuf/response_pb2.py
glide_shared/protobuf_codec.py
glide_shared/routes.py
glide/glide.pypy310-pp73-darwin.so
valkey_glide-2.2.6.dist-info/RECORD
